MANIFEST.in
README.md
setup.py
rv_schubert_sdk/__init__.py
rv_schubert_sdk/rv_schubert_sdk.py
rv_schubert_sdk.egg-info/PKG-INFO
rv_schubert_sdk.egg-info/SOURCES.txt
rv_schubert_sdk.egg-info/dependency_links.txt
rv_schubert_sdk.egg-info/requires.txt
rv_schubert_sdk.egg-info/top_level.txt
rv_schubert_sdk/resources/__init__.py
rv_schubert_sdk/resources/comprovante.py
rv_schubert_sdk/resources/exceptions.py
rv_schubert_sdk/resources/rv_api.py
rv_schubert_sdk/resources/transacao_1.py
rv_schubert_sdk/resources/transacao_3.py
rv_schubert_sdk/resources/transacao_5.py
rv_schubert_sdk/resources/transacao_7.py
rv_schubert_sdk/resources/transacao_9.py
rv_schubert_sdk/resources/objetos/__init__.py
rv_schubert_sdk/resources/objetos/operadora.py
rv_schubert_sdk/resources/objetos/produto.py
rv_schubert_sdk/resources/objetos/recarga.py