Metadata-Version: 1.0
Name: rv-schubert-sdk
Version: 1.1.0
Summary: SDK de integracao com RV Tecnologia
Home-page: https://github.com/rfschubert/rv-schubert-sdk
Author: Raphael Schubert
Author-email: rfswdp@gmail.com
License: UNKNOWN
Platform: UNKNOWN
